mu/__init__.py
mu/__main__.py
mu/tox.ini
python_mu-1.0.3.dist-info/DESCRIPTION.rst
python_mu-1.0.3.dist-info/METADATA
python_mu-1.0.3.dist-info/RECORD
python_mu-1.0.3.dist-info/WHEEL
python_mu-1.0.3.dist-info/entry_points.txt
python_mu-1.0.3.dist-info/metadata.json
python_mu-1.0.3.dist-info/top_level.txt
