Metadata-Version: 2.0
Name: python-mu
Version: 1.0.3
Summary: Python module and CLI to package and upload python lambda functions to AWS Lambda.
Home-page: https://github.com/sivel/mu
Author: Matt Martz
Author-email: matt@sivel.net
License: Apache License, Version 2.0
Keywords: aws amazon lambda
Platform: UNKNOWN
Classifier: Development Status :: 4 - Beta
Classifier: Programming Language :: Python
Classifier: Environment :: Console
Classifier: Operating System :: POSIX
Classifier: Programming Language :: Python :: 2
Classifier: Programming Language :: Python :: 2.7
Classifier: Programming Language :: Python :: 3
Classifier: Intended Audience :: Developers
Classifier: Natural Language :: English
Classifier: Topic :: Utilities
Classifier: License :: OSI Approved :: Apache Software License
Requires-Dist: boto3 (==1.2.1)
Requires-Dist: botocore (==1.3.1)
Requires-Dist: py (==1.4.30)
Requires-Dist: setuptools (==18.4)
Requires-Dist: tox (==2.1.1)
Requires-Dist: virtualenv (==13.1.2)
